./README.md
./pyproject.toml
./tests/test_bench.py
./tests/test_performance.py
./tests/test_vad.py
./vad/__init__.py
./vad/vad.py
getstream_plugins_silero-0.1.0.dist-info/METADATA
getstream_plugins_silero-0.1.0.dist-info/WHEEL
getstream_plugins_silero-0.1.0.dist-info/RECORD
