Metadata-Version: 2.4
Name: getstream-plugins-silero
Version: 0.1.0
Summary: Silero plugin for GetStream
License-Expression: MIT
Requires-Python: >=3.10
Requires-Dist: getstream-plugins-common
Requires-Dist: getstream[webrtc]
Requires-Dist: numpy<2.3,>=2.2.6
Requires-Dist: silero>=0.4.1
Requires-Dist: torch>=2.7.1
